{
    "aboutUsDescriptionFirst": "Есть ли у нас крутая или романтическая история создания бренда? Нет. Зато у нас есть много классных скетчбуков! Присоединяйтесь! ;)",
    "aboutUsDescriptionSecond": "Тестовое описание",
    "aboutUsHeader": "О нас",
    "adminPanel": "Admin Panel",
    "accountOrderDetailsHeader": "Детали заказа",
    "accountOrdersHeader": "Последний заказ",
    "accountTitle": "Мой Аккаунт",
    "addButton": "Добавить",
    "addDetails": "Добавить детали",
    "address": "Адрес",
    "addresses": "Адреса",
    "addToCart": "В корзину",
    "adminCollectionsHeader": "Коллекции",
    "adminContentsEditHeader": "Редактаривание контента",
    "adminContentsHeader": "Контент",
    "adminCustomersHeader": "Покупатели",
    "adminDashboardHeader": "Панель",
    "adminOrderHeader": "Заказы",
    "adminOrdersEditHeader": "Детали заказа",
    "adminPrimaryBrandHeader": "Основной бренд",
    "adminProductsEditHeader": "Редактировать товар",
    "adminProductsHeader": "Товары",
    "article": "Статья",
    "articleNotFound": "Статья не найдена",
    "articlesHeadline": "описание статей",
    "articlesListingHeader": "{appTitle} статья",
    "backButton": "Назад",
    "banner": "Баннер",
    "bannerImageLabel": "URL картинки для баннера",
    "billingDetails": "Платежная информация",
    "billingInformation": "Информация об оплате",
    "cancel": "Отмена",
    "cancelButton": "Отмена",
    "catalogHeading": "Каталог",
    "categories": "Категории",
    "category": "Категория",
    "changePassword": "Сменить Пароль",
    "checkout": "Заказать",
    "checkoutButton": "Заказать",
    "checkoutHeader": "Оформить заказ",
    "city": "Город",
    "COD": "наложенный платеж",
    "collection": "Коллекция",
    "collectionNameHeading": "Название",
    "collectionNewModalTitle": "Создать новую коллекцию",
    "collectionParentHeading": "Родительская коллекция",
    "collections": "Коллекции",
    "comment": "Комментарий",
    "commentComments": "{total, plural, =0 {Нет комментариев} =1 {# Комментарий} few {# Комментария} many {# Комментариев}}",
    "commentLogin": "авторизироваться",
    "commentRegister": "зарегистрироваться",
    "commentSubmit": "Submit",
    "confirmingAccount": "Поддтверждение аккаунта",
    "confirmPassword": "Подтвердите пароль",
    "contents": "Наполнение",
    "continueShopping": "Продолжить покупки",
    "country": "Страна",
    "createdAt": "Создан",
    "createdAtHeading": "Зарегистрировался",
    "creatingOrder": "Оформить заказ",
    "crossSell": "Больше из этой коллекции",
    "currency": "Валюта",
    "customer": "Покупатель",
    "customerDetails": "Контактные данные",
    "customers": "Покупатели",
    "dashboard": "Главная",
    "dateHeading": "Дата",
    "deleteAddress": "Удалить Адрес",
    "deleteAddressConfirm": "Are you sure you want to delete the address?",
    "deleteButton": "Удалить",
    "deliveryHeader": "Доставка и оплата",
    "deliveryLink": "Доставка и оплата",
    "deliveryPaymentDescription": "Оплатить заказ можно следующим образом:",
    "deliveryPaymentMethodInPerson": "наличными при личной встрече",
    "deliveryPaymentMethodPOD": "наложеный платеж при получении на почте",
    "deliveryPaymentMethodPrivatBank": "денежный перевод на карту Приватбанка",
    "deliveryPaymentTitle": "Способ оплаты",
    "deliveryShippingDescription": "Тщательно упаковываем наших терьерчиков и как можно быстрее отправляем Вам удобным для Вас способом:",
    "deliveryShippingMethodInPerson": "личная встреча в Киеве или Харькове (Киев: на Позняках; Харьков: центр или в метро)",
    "deliveryShippingMethodNovaPoshta": "Новая Почта(адресная или до отделения, согласно тарифам)",
    "deliveryShippingMethodUkrPoshta": "Укрпочта (согласно тарифам)",
    "deliveryShippingTitle": "Способ доставки",
    "description": "Описание",
    "descriptionLabel": "Описание",
    "details": "Подробности",
    "disabled": "Ваш аккаунт не активирован",
    "edit": "Редактировать",
    "editAddress": "Редактировать адрес",
    "editButton": "Редактировать",
    "editCollectionsHeader": "Редактирование коллекции",
    "editDetails": "Редактировать ",
    "email": "Email",
    "emailHeading": "Email",
    "emptyCart": "Корзина пуста",
    "enabledHeading": "Включена",
    "fieldRequired": "Обязательное поле",
    "forgotPassword": "Забыли пароль?",
    "freeShipping": "Бесплатная доставка при заказе от",
    "fullName": "Фамилия Имя (полностью)",
    "gallery": "Галерея",
    "hi": "Здравствуйте",
    "history": "История",
    "homepage": "Главная",
    "homepageCheckbox": "На Главной",
    "homepageFeatured": "В рекомендуемых на главной",
    "homepageFeaturedCollections": "Рекомендованные категории и коллекции",
    "homepageSettingsTitle": "Настройки главной страницы",
    "id": "ID",
    "idHeading": "ID",
    "imagesHeading": "Изображения",
    "infoLink": "О нас",
    "infoTitle": "Информация",
    "inPerson": "Самовывоз",
    "invalidArticle": "Нет такой статьи",
    "invalidCredentials": "Недопустимые данные",
    "leaveComment": "Оставьте свой комментарий",
    "link": "Ссылка",
    "listPrice": "Оптовая цена",
    "loggingIn": "Вход",
    "login": "Логин",
    "loginButton": "Войти",
    "loginHeader": "Вход",
    "logoutButton": "Выйти",
    "logoutFirst": "Для того чтобы поддтвердить аккаунт, сначала необходимо выйти из системы",
    "logoutHeader": "Выход",
    "mainCategory": "Главная категория",
    "mainCollection": "Главная коллекция",
    "mainNavigation": "В меню",
    "mainNavigationSettingsTitle": "Порядок главного меню",
    "mergeCartsConfirm": "Ваша корзина не пуста. Вы хотите добавить продукты к текущей корзине? (Если вы скажете «нет», ваша текущая корзина будет очищена)",
    "mergeCartsTitle": "Добавить продукты",
    "metroStation": "Станция метро",
    "myAccount": "Мой аккаунт",
    "myAccount": "Мой аккаунт",
    "myAccount": "Мой аккаунт",
    "name": "Название",
    "nameFullHeading": "Имя",
    "nameHeading": "Название",
    "newAddress": "Новый адрес",
    "newButton": "Создать",
    "newContentModalTitle": "Добавить контент",
    "newPassword": "Новый пароль",
    "newProductModalTitle": "Добавить новый продукт",
    "newsletterCta": "Вам понравилась статья?",
    "newsletterDescription": "Хотите узнавать новости первым!",
    "newsletterPlaceholder": "Введите ваш емейл",
    "newsletterSubmitButton": "Подписаться",
    "newsletterTitle": "Новости",
    "next": "Следующая",
    "no": "Нет",
    "noComments": "Будьте первым, кто оставит комментарий",
    "noOrders": "У вас еще нет заказов :(",
    "noResults": "Нет результатов",
    "noType": "Не установлено",
    "noUser": "Чтобы оставить комментарий,вы должны сначала {login} или {register}.",
    "oldPassword": "Старый пароль",
    "orderBanners": "Настроить порядок баннеров",
    "orderCreated": "Заказ создан",
    "orderCreatedSuccessfully": "Заказ оформлен! Мы свяжемся с вами в ближайшее время",
    "orderError": "Во время оформления заказа произошла ошибка",
    "orderModalTitle": "Спасибо за заказ!",
    "orderPaid": "Оплата отримана",
    "orderPendingPayment": "Нагадати про оплату",
    "orders": "Заказы",
    "orderSummary": "Детали заказа",
    "orderSummaryName": "Наименование",
    "outOfStock": "Нет в наличии",
    "pagination": "Страница {currentPage} из {totalPages}",
    "parentCollection": "Родительская коллекция",
    "password": "Новый пароль",
    "password": "Пароль",
    "password": "Пароль",
    "passwordConfirm": "Подтвердите пароль",
    "passwordConfirm": "Подтвердить пароль",
    "passwordMismatch": "Пароле не совпадают",
    "passwordMismatch": "Пароли не совпадают",
    "passwordMismatch": "Пароли не совпадают",
    "paymentInPerson": "наличными при самовывозе",
    "paymentMethod": "Способ оплати",
    "paymentMethodLabel": "Выберите способ оплаты",
    "pendingConfirmation": "Ваш аккаунт ожидает подтверждения по email",
    "phone": "Телефон",
    "phoneHeading": "Телефон",
    "phoneNumber": "Телефон",
    "postalCode": "Postal Code",
    "preview": "Предварительный просмотр",
    "previous": "Предыдущая",
    "priceHeading": "Цена",
    "pricing": "Цены",
    "primaryBrand": "Бренд",
    "privatBank": "на карту ПриватБанка",
    "productPage": "Страничка товара",
    "productPageCheckbox": "Страничка товара",
    "products": "Товары",
    "productsHeader": "Товары",
    "productsList": "Товары",
    "quantityAndPrice": "Количество / Цена",
    "quantityHeading": "Количество",
    "readMore": "Читать далее",
    "ref": "Код товара",
    "registerButton": "Регистрация",
    "registerHeader": "Зарегистрироваться",
    "resetButton": "Сбросить",
    "resetConfirmHeader": "Сменить пароль",
    "resetConfirmSuccessModalBody": "Для получения доступа к вашему аккаунту, войдите используя новый пароль.",
    "resetConfirmSuccessModalContinue": "Вход",
    "resetConfirmSuccessModalTitle": "Пароль обновлен",
    "resetHeader": "Сбросить пароль",
    "resetSuccessModalBody": "Вскоре вы получите электронное письмо с инструкциями, о том как восстановить пароль.",
    "resetSuccessModalContinue": "OK",
    "resetSuccessModalTitle": "Пароль сброшен",
    "retailPrice": "Розничная цена",
    "saveButton": "Сохранить",
    "savedAddresses": "Выберите один из сохраненных адресов",
    "sections": "Показывать в секциях",
    "sectionsHeading": "Секции",
    "sendButton": "Відіслати",
    "sendEmailButton": "Отправить Email",
    "sendEmailModalTitle": "Отправить Email",
    "shipping": "Доставка",
    "shippingCost": "Стоимость доставки",
    "shippingDetails": "Детали заказа",
    "shippingInformation": "Информация о доставке",
    "shippingMethod": "Способ доставки",
    "shippingMethodAddress": "Адрес доставки",
    "shippingMethodAddressDescription": "Город и номер отделения Новой Почты / почтовый адрес",
    "shippingMethodLabel": "Выберите способ доставки",
    "showAll": "Показать все",
    "sideCartHeader": "Ваша корзина",
    "skuHeading": "Артикул",
    "socialTitle": "Социальные сети",
    "sortAlphabetically": "По алфавиту: А-Я",
    "sortAlphabeticallyReverse": "По алфавиту: Я-А",
    "sortBestSelling": "Популярные",
    "sortFeatured": "Рекомендованые",
    "sortLabel": "Сортировать",
    "sortOldest": "По дате (сначала старые)",
    "sortPrice": "Сначала девешые",
    "sortPriceReverse": "Сначала дорогие",
    "sortRecent": "Новинки",
    "state": "Область",
    "status": "Статус",
    "status_canceled": "Отмененный",
    "status_created": "Созданный",
    "status_paid": "Оплаченый",
    "status_paymentError": "Ошибка оплаты",
    "status_pendingPayment": "Ожидает оплаты",
    "status_processing": "В обработке",
    "status_ready": "Готов",
    "status_shipped": "Отправленный",
    "statusHeading": "Статус",
    "stockHeading": "Запас",
    "subject": "Тема",
    "subtotal": "Итого",
    "subTotal": "Промежуточный итог",
    "registerSuccessModalBody": "Письмо со ссылкой для активации аккаунта было отправлено на вашу почту. Спасибо за регистрацию!",
    "registerSuccessModalContinue": "ОК",
    "registerSuccessModalTitle": "Аккаунт Создан",
    "suggestedArticles": "Похожие статьи",
    "suggestedProducts": "Рекомендованные товары",
    "summary": "Краткое изложение",
    "tagsHeading": "Тэги",
    "template": "Шаблон",
    "total": "Итого",
    "total": "Итого",
    "translationsHeading": "Переводы",
    "tryAgain": "Попробуйте еще раз",
    "type": "Тип",
    "typeHeading": "Тип",
    "ukrPoshta": "Укрпочта",
    "unknownError": "Ошибка. Пожалуйста, свяжитесь со службой поддержки",
    "unknownStatus": "Ошибка. Пожалуйста, свяжитесь со службой поддержки",
    "unsupportedType": "Неподдерживаемый тип контента",
    "updateButton": "Обновить",
    "updateModalTitle": "Обновить статус",
    "uploadButton": "Загрузить",
    "uploadProductsModalTitle": "Загрузить товары",
    "url": "URL",
    "useShippingAddress": "Использовать адрес доставки для выставления счета",
    "validNumber": "Пожалуйста, укажите правильный номер телефона",
    "vat": "Налог, %",
    "vatLabel": "ИНН",
    "vatin": "ИНН",
    "viewAllArticles": "Смотреть все статьи",
    "viewDetails": "Подробности",
    "viewURL": "URL",
    "whatsMissing": "Что пропущено?",
    "yes": "Да",
    "zipCode": "Индекс"
}
